cddp/__init__.py
cddp/dbxapi.py
cddp/utils.py
cddp/ingestion/__init__.py
cddp/ingestion/autoloader.py
cddp/ingestion/azure_adls_gen1.py
cddp/ingestion/azure_adls_gen2.py
cddp/ingestion/azure_eventhub.py
cddp/ingestion/deltalake.py
cddp/ingestion/filestore.py
cddp/ingestion/jdbc.py
cddp-0.0.9.dist-info/LICENSE
cddp-0.0.9.dist-info/LICENSE-CODE
cddp-0.0.9.dist-info/METADATA
cddp-0.0.9.dist-info/WHEEL
cddp-0.0.9.dist-info/top_level.txt
cddp-0.0.9.dist-info/RECORD
