Metadata-Version: 2.1
Name: cddp
Version: 0.0.9
Summary: Config Driven Data Pipeline
Home-page: https://github.com/azure/config-driven-data-pipeline
Author: Sean Ma
Author-email: maye-msft@outlook.com
Project-URL: Bug Tracker, https://github.com/azure/config-driven-data-pipeline/issues
Classifier: Programming Language :: Python :: 3
Classifier: License :: OSI Approved :: Apache Software License
Classifier: Operating System :: OS Independent
Requires-Python: >=3.8
License-File: LICENSE
License-File: LICENSE-CODE
